maudecli/__init__.py
maudecli/api.py
maudecli/db.py
maudecli/errors.py
maudecli/formatters.py
maudecli/resources/READEME.txt
maudecli/utils.py
maude_cli-0.3.1.dist-info/WHEEL
maude_cli-0.3.1.dist-info/entry_points.txt
maude_cli-0.3.1.dist-info/METADATA
maude_cli-0.3.1.dist-info/RECORD
