Metadata-Version: 2.3
Name: maude-cli
Version: 0.3.1
Summary: Command-line interface to search MAUDE database for medical device adverse events via openFDA API
Requires-Python: >=3.12
